boosty_dl/__init__.py
boosty_dl/__main__.py
boosty_dl/api.py
boosty_dl/auth.py
boosty_dl/cli.py
boosty_dl/core.py
boosty_dl/email.py
boosty_dl/jellyfin.py
boosty_dl/lock.py
boosty_dl/media.py
boosty_dl/plex.py
boosty_dl/util.py
boosty_dl-2.0.5.dist-info/licenses/LICENSE
boosty_dl-2.0.5.dist-info/METADATA
boosty_dl-2.0.5.dist-info/WHEEL
boosty_dl-2.0.5.dist-info/entry_points.txt
boosty_dl-2.0.5.dist-info/top_level.txt
boosty_dl-2.0.5.dist-info/RECORD
