Metadata-Version: 2.4
Name: boosty-dl
Version: 2.0.5
Summary: Download videos from Boosty channels
Author: Artem Butusov
License: MIT
Project-URL: Homepage, https://github.com/sormy/boosty-downloader
Project-URL: Issues, https://github.com/sormy/boosty-downloader/issues
Keywords: boosty,video,download,media
Classifier: Environment :: Console
Classifier: Intended Audience :: End Users/Desktop
Classifier: License :: OSI Approved :: MIT License
Classifier: Operating System :: POSIX :: Linux
Classifier: Operating System :: MacOS
Classifier: Programming Language :: Python :: 3
Classifier: Programming Language :: Python :: 3.11
Classifier: Programming Language :: Python :: 3.12
Classifier: Programming Language :: Python :: 3.13
Classifier: Programming Language :: Python :: 3.14
Classifier: Topic :: Multimedia :: Video
Requires-Python: >=3.11
License-File: LICENSE
Requires-Dist: mutagen~=1.45
Provides-Extra: dev
Requires-Dist: black; extra == "dev"
Requires-Dist: build; extra == "dev"
Requires-Dist: flake8; extra == "dev"
Requires-Dist: pyright; extra == "dev"
Requires-Dist: pytest; extra == "dev"
Requires-Dist: twine; extra == "dev"
Dynamic: license-file
